{ 
    
    "board_background": [
        {
            "shape": [ 941,248, 33,21, 1919,61, 1919,248 ]
        },
        {
            "shape": [ 860,893, -5,1075, 374,778, 824,779, 861,832 ]
        },
        {
            "shape": [ 941,248, 1566,249, 1460,357, 1030,355 ]
        },
        {
            "shape": [ 376,249, 33,21, 941,248 ]
        },
        {
            "shape": [ 376,249, 291,336, 4,526, 33,21 ]
        },
        {
            "shape": [ 1917,1081, -5,1075, 903,925, 1922,923 ]
        },
        {
            "shape": [ 288,681, -5,1075, 4,526, 291,336 ]
        },
        {
            "shape": [ 374,778, -5,1075, 288,681 ]
        },
        {
            "shape": [ -5,1075, 860,893, 903,925 ]
        }
    ]
}
